CMakeLists.txt
LICENSE
MANIFEST.in
README.md
setup.py
cmake/googletest.cmake
cmake/moderngpu.cmake
cmake/pybind11.cmake
cmake/select_compute_arch.cmake
cmake/torch.cmake
cmake/Modules/FetchContent.cmake
cmake/Modules/FindValgrind.cmake
cmake/Modules/README.md
cmake/Modules/FetchContent/CMakeLists.cmake.in
optimized_transducer/CMakeLists.txt
optimized_transducer.egg-info/PKG-INFO
optimized_transducer.egg-info/SOURCES.txt
optimized_transducer.egg-info/dependency_links.txt
optimized_transducer.egg-info/not-zip-safe
optimized_transducer.egg-info/top_level.txt
optimized_transducer/csrc/CMakeLists.txt
optimized_transducer/csrc/cpu.cc
optimized_transducer/csrc/cuda.cu
optimized_transducer/csrc/kernels.cu
optimized_transducer/csrc/kernels.h
optimized_transducer/csrc/moderngpu-allocator.h
optimized_transducer/csrc/transducer-loss.cc
optimized_transducer/csrc/transducer-loss.h
optimized_transducer/python/CMakeLists.txt
optimized_transducer/python/csrc/CMakeLists.txt
optimized_transducer/python/csrc/optimized_transducer.cc
optimized_transducer/python/csrc/optimized_transducer.h
optimized_transducer/python/optimized_transducer/__init__.py
optimized_transducer/python/optimized_transducer/torch_version.py.in
optimized_transducer/python/optimized_transducer/transducer_loss.py
optimized_transducer/python/tests/CMakeLists.txt
optimized_transducer/python/tests/test_compute_transducer_loss.py
optimized_transducer/python/tests/test_cuda.py
optimized_transducer/python/tests/test_log_softmax.py
optimized_transducer/python/tests/test_max_symbol_per_frame.py