Metadata-Version: 2.1
Name: optimized-transducer
Version: 1.4
Summary: UNKNOWN
Home-page: https://github.com/csukuangfj/optimized_transducer
Author: Fangjun Kuang
Author-email: csukuangfj@gmail.com
License: Apache licensed, as found in the LICENSE file
Platform: UNKNOWN
Classifier: Programming Language :: C++
Classifier: Programming Language :: Python
Classifier: Topic :: Scientific/Engineering :: Artificial Intelligence
